{
  "type": "Feature",
  "properties": {
    "iso:country":"SI",
    "sg:address":"Cesta V Zgornji Log 89",
    "sg:city":"Ljubljana",
    "sg:classifiers":[
        {
            "category":"Professional",
            "subcategory":"Computer Services",
            "type":"Services"
        }
    ],
    "sg:postcode":"1000",
    "sg:tags":[
        "virtual-assistants",
        "natural-language-interaction",
        "virtual-agent",
        "online-slaes",
        "cutomer-service-optimization"
    ],
    "sg:website":"http://www.artificial-solutions.com",
    "wof:name":"Artificial Solutions",
    "wof:placetype":"venue"
},
  "geometry": {"coordinates":[14.4593277,46.0308118],"type":"Point"}
}